MANIFEST.in
README.rst
setup.cfg
setup.py
pyfluent/__init__.py
pyfluent/client.py
pyfluent/logging.py
pyfluent.egg-info/PKG-INFO
pyfluent.egg-info/SOURCES.txt
pyfluent.egg-info/dependency_links.txt
pyfluent.egg-info/requires.txt
pyfluent.egg-info/top_level.txt