Metadata-Version: 1.0
Name: pyfluent
Version: 0.2.0
Summary: A python client library for Fluentd
Home-page: https://github.com/yosisa/pyfluent
Author: Yoshihisa Tanaka
Author-email: yt.hisa@gmail.com
License: MIT
Keywords: logging,fluentd,json
Platform: UNKNOWN
Classifier: Programming Language :: Python
Classifier: Programming Language :: Python :: 3
Classifier: License :: OSI Approved :: Apache Software License
Classifier: Operating System :: OS Independent
Classifier: Development Status :: 3 - Alpha
Classifier: Intended Audience :: Developers
Classifier: Topic :: Software Development :: Libraries :: Python Modules
Classifier: Topic :: System :: Logging
Classifier: Topic :: System :: Networking
